plainx/sentry/CHANGELOG.md
plainx/sentry/__init__.py
plainx/sentry/config.py
plainx/sentry/default_settings.py
plainx/sentry/templates.py
plainx/sentry/templates/sentry/js.html
plainx_sentry-0.9.0.dist-info/METADATA
plainx_sentry-0.9.0.dist-info/WHEEL
plainx_sentry-0.9.0.dist-info/RECORD
