Metadata-Version: 2.4
Name: plainx-sentry
Version: 0.9.0
Author-email: Dave Gaeddert <dave.gaeddert@gmail.com>
Requires-Python: >=3.11
Requires-Dist: plain-auth>=0.16.0
Requires-Dist: plain-sessions>=0.27.0
Requires-Dist: sentry-sdk[opentelemetry]>=2.24.0
